fw_gear_file_classifier/__init__.py
fw_gear_file_classifier/classification_profiles/CT/CT.yaml
fw_gear_file_classifier/classification_profiles/CT/CT_check_classification.yaml
fw_gear_file_classifier/classification_profiles/CT/CT_fallback.yaml
fw_gear_file_classifier/classification_profiles/CT/main.yaml
fw_gear_file_classifier/classification_profiles/CT/select_modality.yaml
fw_gear_file_classifier/classification_profiles/MG.yaml
fw_gear_file_classifier/classification_profiles/MR/GE.yaml
fw_gear_file_classifier/classification_profiles/MR/MR_fallback.yaml
fw_gear_file_classifier/classification_profiles/MR/PHILIPS/DWI.yaml
fw_gear_file_classifier/classification_profiles/MR/PHILIPS/FLAIR.yaml
fw_gear_file_classifier/classification_profiles/MR/PHILIPS/Localizer.yaml
fw_gear_file_classifier/classification_profiles/MR/PHILIPS/PD.yaml
fw_gear_file_classifier/classification_profiles/MR/PHILIPS/SWI.yaml
fw_gear_file_classifier/classification_profiles/MR/PHILIPS/T1.yaml
fw_gear_file_classifier/classification_profiles/MR/PHILIPS/T2*.yaml
fw_gear_file_classifier/classification_profiles/MR/PHILIPS/T2.yaml
fw_gear_file_classifier/classification_profiles/MR/PHILIPS/features.yaml
fw_gear_file_classifier/classification_profiles/MR/PHILIPS/main.yaml
fw_gear_file_classifier/classification_profiles/MR/SIEMENS.yaml
fw_gear_file_classifier/classification_profiles/MR/check_measurement.yaml
fw_gear_file_classifier/classification_profiles/MR/classify_intent.yaml
fw_gear_file_classifier/classification_profiles/MR/main.yaml
fw_gear_file_classifier/classification_profiles/MR/select_manufacturer.yaml
fw_gear_file_classifier/classification_profiles/PT.yaml
fw_gear_file_classifier/classification_profiles/__init__.py
fw_gear_file_classifier/classification_profiles/example.yaml
fw_gear_file_classifier/classification_profiles/fw-modality-classification.yaml
fw_gear_file_classifier/classification_profiles/main.yaml
fw_gear_file_classifier/main.py
fw_gear_file_classifier/parser.py
fw_gear_file_classifier-1.0.0.dist-info/LICENSE
fw_gear_file_classifier-1.0.0.dist-info/METADATA
fw_gear_file_classifier-1.0.0.dist-info/WHEEL
fw_gear_file_classifier-1.0.0.dist-info/RECORD
